spacy_ke/__init__.py
spacy_ke/about.py
spacy_ke/base.py
spacy_ke/positionrank.py
spacy_ke/textrank.py
spacy_ke/topicrank.py
spacy_ke/util.py
spacy_ke/yake.py
spacy_ke-0.1.4.dist-info/LICENSE
spacy_ke-0.1.4.dist-info/METADATA
spacy_ke-0.1.4.dist-info/WHEEL
spacy_ke-0.1.4.dist-info/top_level.txt
spacy_ke-0.1.4.dist-info/RECORD
