Metadata-Version: 2.1
Name: spacy-ke
Version: 0.1.4
Summary: Keyword extraction with spaCy
Home-page: https://github.com/talmago/spacy_ke
Author: Tal Almagor
Author-email: almagoric@gmail.com
License: GPL
Platform: UNKNOWN
Classifier: Intended Audience :: Developers
Classifier: Intended Audience :: Science/Research
Classifier: License :: OSI Approved :: MIT License
Classifier: Programming Language :: Python :: 3
Classifier: Programming Language :: Python :: 3.6
Classifier: Programming Language :: Python :: 3.7
Classifier: Programming Language :: Python :: 3.8
Classifier: Topic :: Scientific/Engineering
Requires-Python: >=3.6
Requires-Dist: editdistance
Requires-Dist: networkx
Requires-Dist: scipy (>=1.5)
Requires-Dist: numpy (>=1.15.0)
Requires-Dist: dataclasses (<1.0,>=0.6) ; python_version < "3.7"
